{
  "tasks": [
    {
      "userId": "1",
      "date": "08-07-2024",
      "title": "Заголовок 1",
      "description": "Описание 1",
      "id": "334389439348943",
      "status": "Активна"
    },
    {
      "userId": "2",
      "date": "08-07-2024",
      "title": "Заголовок 2",
      "description": "Описание 2",
      "id": "5408904930439403",
      "status": "Активна"
    },
    {
      "id": "1720693613356",
      "title": "1",
      "status": "Активна",
      "description": "2",
      "date": "11-07-2024"
    },
    {
      "id": "1720694336276",
      "title": "1",
      "status": "Активна",
      "description": "2",
      "date": "11-07-2024"
    }
  ]
}